Metadata-Version: 2.1
Name: bio-tools-26
Version: 0.1.0
Summary: A collection of bioinformatics tools and notebooks
Home-page: https://github.com/yourusername/bio
Author: Your Name
Author-email: your.email@example.com
Classifier: Programming Language :: Python :: 3
Classifier: License :: OSI Approved :: MIT License
Classifier: Operating System :: OS Independent
Requires-Python: >=3.6
